{
  "ahmad al sharaa": "ent_person_ahmad_al_sharaa",
  "ahmed al sharaa": "ent_person_ahmad_al_sharaa",
  "ali khamenei": "ent_person_ali_khamenei",
  "ali shaath": "ent_person_ali_shaath",
  "anastasiia berezovska": "ent_person_anastasiia_berezovska",
  "ankara": "ent_location_ankara",
  "ankara province": "ent_location_ankara",
  "ankara turkey": "ent_location_ankara",
  "arabian sea": "ent_location_arabian_sea",
  "bashar al assad": "ent_person_bashar_al_assad",
  "benjamin netanyahu": "ent_person_benjamin_netanyahu",
  "board of peace": "ent_organization_board_of_peace",
  "boeing 737": "ent_technology_boeing_737_400",
  "boeing 737 400": "ent_technology_boeing_737_400",
  "central damascus": "ent_location_syria",
  "crimea": "ent_location_crimea",
  "damascus": "ent_location_syria",
  "donald trump": "ent_person_donald_trump",
  "elysee palace": "ent_organization_french_government",
  "emmanuel macron": "ent_person_emmanuel_macron",
  "f 35": "ent_technology_f_35_lightning_ii",
  "f 35 fighter jets": "ent_technology_f_35_lightning_ii",
  "f 35 lightning ii": "ent_technology_f_35_lightning_ii",
  "f 35s": "ent_technology_f_35_lightning_ii",
  "flightradar24": "ent_technology_flightradar24",
  "four seasons hotel": "ent_location_four_seasons_hotel_damascus",
  "four seasons hotel damascus": "ent_location_four_seasons_hotel_damascus",
  "french government": "ent_organization_french_government",
  "french presidential convoy": "ent_organization_french_government",
  "gaza": "ent_location_gaza_strip",
  "gaza strip": "ent_location_gaza_strip",
  "government of the french republic": "ent_organization_french_government",
  "hamas": "ent_organization_hamas",
  "hegseth": "ent_person_pete_hegseth",
  "hur": "ent_organization_main_directorate_of_intelligence",
  "interpol": "ent_organization_interpol",
  "iran": "ent_organization_iran",
  "iran s revolutionary guards": "ent_organization_islamic_revolutionary_guard_corps",
  "iranian": "ent_organization_iran",
  "iranian president masoud pezeshkian": "ent_person_masoud_pezeshkian",
  "islamic revolutionary guard corps": "ent_organization_islamic_revolutionary_guard_corps",
  "israel": "ent_organization_israel",
  "israel katz": "ent_person_israel_katz",
  "israeli": "ent_organization_israel",
  "israeli defence minister israel katz": "ent_person_israel_katz",
  "k2 airways": "ent_organization_k2_airways",
  "karachi": "ent_location_karachi",
  "khamenei": "ent_person_ali_khamenei",
  "kyiv": "ent_location_kyiv",
  "lockheed martin f 35 lightning ii": "ent_technology_f_35_lightning_ii",
  "macron": "ent_person_emmanuel_macron",
  "main directorate of intelligence": "ent_organization_main_directorate_of_intelligence",
  "masoud pezeshkian": "ent_person_masoud_pezeshkian",
  "military intelligence service hur": "ent_organization_main_directorate_of_intelligence",
  "mohammed al farra": "ent_person_mohammed_al_farra",
  "mojtaba khamenei": "ent_person_mojtaba_khamenei",
  "monaco": "ent_location_monaco",
  "national committee for the administration of gaza": "ent_organization_national_committee_for_the_administration_of_gaza",
  "nato": "ent_organization_nato",
  "nato allies": "ent_organization_nato",
  "ncag": "ent_organization_national_committee_for_the_administration_of_gaza",
  "netanyahu": "ent_person_benjamin_netanyahu",
  "pakistan civil aviation authority": "ent_organization_pakistan_civil_aviation_authority",
  "patriot": "ent_technology_patriot_missile_system",
  "patriot interceptor missiles": "ent_technology_patriot_missile_system",
  "patriot missile system": "ent_technology_patriot_missile_system",
  "patriot missiles": "ent_technology_patriot_missile_system",
  "pete hegseth": "ent_person_pete_hegseth",
  "president trump": "ent_person_donald_trump",
  "prime minister netanyahu": "ent_person_benjamin_netanyahu",
  "prime minister shehbaz sharif": "ent_person_shehbaz_sharif",
  "putin": "ent_person_vladimir_putin",
  "russia": "ent_organization_russia",
  "russian": "ent_organization_russia",
  "russian president vladimir putin": "ent_person_vladimir_putin",
  "sharjah": "ent_location_sharjah",
  "sharjah uae": "ent_location_sharjah",
  "shehbaz sharif": "ent_person_shehbaz_sharif",
  "strait of hormuz": "ent_location_strait_of_hormuz",
  "syria": "ent_location_syria",
  "syrian interior ministry": "ent_organization_syrian_interior_ministry",
  "trump": "ent_person_donald_trump",
  "turkey": "ent_location_turkey",
  "ukraine": "ent_location_ukraine",
  "ukrainian president volodymyr zelensky": "ent_person_volodymyr_zelensky",
  "ukrainian president zelensky": "ent_person_volodymyr_zelensky",
  "united states": "ent_organization_united_states",
  "us": "ent_organization_united_states",
  "us president donald trump": "ent_person_donald_trump",
  "vadym yermolaiev": "ent_person_vadym_yermolaiev",
  "vladimir putin": "ent_person_vladimir_putin",
  "volodymyr zelensky": "ent_person_volodymyr_zelensky",
  "volodymyr zelenskyy": "ent_person_volodymyr_zelensky",
  "zelensky": "ent_person_volodymyr_zelensky"
}